{
  "id": "fig-and-thyme-clafoutis",
  "name": "Fig and thyme clafoutis",
  "source": {
    "cookbook": "Ottolenghi Simple",
    "author": "Yotam Ottolenghi"
  },
  "servings": "serves 4",
  "intro": "surprised how much everyone can eat. The gs can be made 2 days ahead and",
  "ingredients": [
    {
      "item": "tbsp/90g dark muscovado sugar",
      "amount": "7"
    },
    {
      "item": "water",
      "amount": "1 tbsp"
    },
    {
      "item": "red wine",
      "amount": "2 tbsp"
    },
    {
      "item": "thyme leaves",
      "amount": "1 tbsp"
    },
    {
      "item": "lemons:  nely zest to get 2 tsp, then juice to get 1 tbsp",
      "amount": "2"
    },
    {
      "item": "oz/420g really ripe Mission figs (about 10, depending on size), tough stems removed, halved lengthwise",
      "amount": "14¾"
    },
    {
      "item": "large eggs, yolks and whites separated",
      "amount": "2"
    },
    {
      "item": "cup/50g all-purpose flour",
      "amount": "⅓"
    },
    {
      "item": "vanilla extract",
      "amount": "1½ tsp"
    },
    {
      "item": "tbsp/100ml heavy cream",
      "amount": "7"
    },
    {
      "item": "salt vanilla ice cream (or crème fraîche, to serve)",
      "amount": "⅛ tsp"
    },
    {
      "item": "1.",
      "amount": ""
    },
    {
      "item": "2.",
      "amount": ""
    }
  ],
  "method": [
    "Put 4 tbsp/50g of the sugar into a small ovenproof high-sided sauté pan (about 7 inches/18cm), along with the water. (If you don’t have an ovenproof pan this size, cook the  gs in a regular frying pan and transfer them to a 9-inch/22cm baking dish.) Place over medium-high heat for 3–4 minutes, swirling the pan a few times, until the sugar has completely melted and is bubbling rapidly. Carefully add the wine and thyme and stir continuously for about 1 minute, keeping the pan on the heat, until combined and thick. Remove from the heat, stir in the lemon juice and  gs, and set aside to cool for 20 minutes (or longer)—you just don’t want them to be piping hot when the topping gets poured on. If you need to transfer the  gs to a baking dish, do this now.",
    "Place the egg yolks in a bowl with the remaining 3 tbsp/40g of sugar, the",
    "our, vanilla, cream, lemon zest, and salt. Whisk until pale and thickened: 2–",
    "3 minutes by hand, or 1 minute with a handheld mixer. Whisk the egg whites separately by hand for 1–2 minutes, to form stiff peaks, and fold gently into the batter until just combined.",
    "Spread out the  gs in the sauté pan (or baking dish) and pour in the batter.",
    "Bake for 30 minutes, until the batter has risen and is golden brown and cooked through. Remove from the oven, divide among four bowls, and serve hot with the ice cream or crème fraîche.",
    "Honey and yogurt set cheesecake",
    "No oven, no bain-marie, no cracks—this is the simplest of cheesecakes! You can make this up to 2 days ahead, topping with the honey and thyme just before serving if you like. It will keep in the fridge but the base will soften with time."
  ],
  "time": {
    "total": 30
  },
  "category": {
    "dish_type": [
      "main"
    ],
    "chapter": ""
  },
  "cuisine": "Middle Eastern",
  "dietary": [
    "vegetarian"
  ]
}
