{
  "id": "get-into-oatmeal",
  "name": "Get Into Oatmeal",
  "source": {
    "cookbook": "Jamie's Food Revolution",
    "author": "Jamie Oliver"
  },
  "servings": "serves 4",
  "ingredients": [
    {
      "item": "quick cook oats (not instant)",
      "amount": "2 cups"
    },
    {
      "item": "milk, soy milk, or water",
      "amount": "3 cups"
    }
  ],
  "method": [
    "Place the oats and the milk or water in a saucepan with a small pinch of sea salt and put it on a",
    "medium heat. Bring to a steady simmer for 5 to 6 minutes, stirring as often as you can t o give you",
    "smooth, creamy oatmeal. While it's blipping away in the pan, choose o ne of the flavor co m binat ions",
    "below and prepare the ingredients. I or 2 minutes before the oatmea l is ready, add your flavoring",
    "(see below) • If you like your oatmeal runnier, simply stir in a splash more milk or w a r until you've",
    "got the consistency you're after",
    "Banana and cinnamon",
    "2 ripe bananas, finely sliced",
    "Y2 teaspoon ground cinnamon",
    "2 tablespoons poppy seeds",
    "2-4 tablespoons maple syrup or runny honey, or to",
    "a small handful of toasted sliced almonds or",
    "unsweetened shredded coconut",
    "Banana, whisky, and nutmeg",
    "2 ripe bananas, mashed",
    "shots (!4 cup) of whisky (for grown-ups",
    "only, not for the kids!)",
    "!4 of a nutmeg, finely grated",
    "300 KICK-START BREAKFASTS",
    "Blackberry and apple",
    "2 apples, cored and diced",
    "a tablespoon of butter",
    "a small extra handful of uncooked oats",
    "I tablespoon honey, plus extra to taste",
    "handfuls of fresh or frozen blackberries",
    "Fry t he apples in a pan with the but t e r unti l soft",
    "and golden. Add the uncooked oatmeal and honey,",
    "ook for I minute • Squash t he blackber ries",
    "the cooked oatmeal • Serve with the apple",
    "Dark chocolate and Seville orange",
    "2 ounces good quality bittersweet (60% cocoa solids",
    "minimum) chocolate, finely grated",
    "heaped !4 cup Seville orange marmalade",
    "ONE-CUP PANCAKES, TROPICAL",
    "YOGURT, AND MANGO",
    "The se are the easiest pancakes to make - you don't even need scales to weigh your ingredients. All you",
    "is a cup or a mug. As long as you us e the same cup for measuring both the flour and the milk,",
    "ll be laughing! If you use self-rising flour t he pancakes will be more American in style, lovely and fluffy",
    "and thick. All-purpose flour will give you thinner ones, more like European crepes. Great with a sprinkling",
    "of sugar and a squeeze of lemon juice (very o ld school!), or drizzled with maple syrup and served with",
    "rispy bacon. Try throwing a handful of blueberries into the batter mix if making American-style pancakes.",
    "I also love eating them with coconut-flava red yogurt , which is delicious. I've given you a recipe here for",
    "ng your own similar t ropical-flavored yogurt. It actually gets better if you let it stand in the fridge for",
    "a few ho urs, as",
    "the coconut w ill soften."
  ],
  "time": {
    "total": 30
  },
  "category": {
    "dish_type": [
      "breakfast"
    ],
    "chapter": "",
    "meal_role": "breakfast"
  }
}
