{
  "id": "grilled-swordfish-with-salmoriglio-sauce",
  "name": "Grilled Swordfish with Salmoriglio Sauce",
  "source": {
    "cookbook": "Four Seasons",
    "author": "Mietta Sartori",
    "chapter": "Spring"
  },
  "servings": "serves 4",
  "intro": "In Sicily swordfish, found in the waters off the island’s long coastline, is much appreciated. Perhaps this is because it has a very delicate flavour, so even people who do not especially like fish will love it. The salmoriglio sauce is a very traditional way to prepare it.",
  "ingredients": [
    {
      "item": "SALMORIGLIO SAUCE",
      "amount": ""
    },
    {
      "item": "good-quality virgin olive oil",
      "amount": "120 ml"
    },
    {
      "item": "warm water",
      "amount": "60 ml"
    },
    {
      "item": "juice of 1 organic lemon",
      "amount": ""
    },
    {
      "item": "cloves garlic, very finely chopped",
      "amount": "2"
    },
    {
      "item": "tablespoon finely chopped fresh oregano",
      "amount": "1"
    },
    {
      "item": "tablespoon finely chopped flat-leaf parsley",
      "amount": "1"
    },
    {
      "item": "small red chilli, partially deseeded and very finely chopped (optional)",
      "amount": "1"
    },
    {
      "item": "× 150 g slices swordfish, about 1 cm thick",
      "amount": "4"
    },
    {
      "item": "tablespoon good-quality virgin olive oil",
      "amount": "1"
    },
    {
      "item": "salt flakes and ground black pepper",
      "amount": ""
    }
  ],
  "method": [
    "Preheat the grill to high.",
    "To prepare the sauce, whisk the oil in a mixing bowl and very slowly add the warm water and lemon juice, whisking continuously to form an emulsion. Add the garlic, herbs and chilli (if using).",
    "Pat the swordfish slices dry with kitchen paper and rub them all over with oil. Grill for around 2 minutes on each side. Remove the fish from the grill and season with salt and pepper. Serve straight away, with the sauce spooned over the fish. Alternatively, serve the sauce on the side in a warm jug."
  ],
  "image": "/recipes/grilled-swordfish-with-salmoriglio-sauce.jpg",
  "time": {
    "total": 2
  },
  "category": {
    "dish_type": [
      "side"
    ],
    "chapter": "Spring"
  },
  "cuisine": "Italian"
}
