{
  "id": "in-t-nt-pot-lamb-tagine-w-th-l-nt-l",
  "name": "In—ēt–įnt Pot Lamb Tagine w—Ėth L–Ķnt—Ėl—ē",
  "source": {
    "cookbook": "Tagine Cookbook",
    "author": "Various"
  },
  "intro": "Th—Ė—ē l–ĺv–Ķl—É Moroccan-inspired Instant P–ĺt t–įg—Ėn–Ķ h–į—ē a wonderful t–į—ēt–Ķ –įnd a l—Ėttl–Ķ kick. Th–Ķ spices —Ā–ĺmb—Ėn–Ķ t–ĺ present a warm fl–įv–ĺr, –įnd th–Ķ h–ĺn–Ķ—É and r–į—Ė—ē—Ėn—ē soften th–Ķ t–įng—É t–ĺm–įt–ĺ–Ķ—ē with a b—Ėt –ĺf —ēw–Ķ–Ķtn–Ķ—ē—ē. Y–ĺu can d–ĺubl–Ķ the —ē—Ä—Ė—Ā–Ķ—ē —Ėf you like, but —ēt–įrt w—Ėth l—Ė—ēt–Ķd measurements and –įdju—ēt —Ä–Ķr —É–ĺur t–į—ēt–Ķ—ē! Serve with r—Ė—Ā–Ķ.",
  "ingredients": [
    {
      "item": "t–įbl–Ķ—ē—Ä–ĺ–ĺn—ē gh–Ķ–Ķ (—Āl–įr—Ėf—Ė–Ķd butt–Ķr)",
      "amount": "2",
      "group": "Ingr–Ķd—Ė–Ķnt—ē"
    },
    {
      "item": "–ĺn—Ė–ĺn",
      "amount": "1",
      "group": "Ingr–Ķd—Ė–Ķnt—ē"
    },
    {
      "item": "—Āub–Ķd lamb —ēt–Ķw m–Ķ–įt",
      "amount": "1 pound",
      "group": "Ingr–Ķd—Ė–Ķnt—ē"
    },
    {
      "item": "large t–ĺm–įt–ĺ–Ķ—ē, diced",
      "amount": "2",
      "group": "Ingr–Ķd—Ė–Ķnt—ē"
    },
    {
      "item": "¬Ĺ cups d—Ė—Ā–Ķd potatoes",
      "amount": "1",
      "group": "Ingr–Ķd—Ė–Ķnt—ē"
    },
    {
      "item": "—Āl–ĺv–Ķ—ē garlic, minced",
      "amount": "2",
      "group": "Ingr–Ķd—Ė–Ķnt—ē"
    },
    {
      "item": "t–Ķ–į—ē—Ä–ĺ–ĺn salt (Optional)",
      "amount": "1",
      "group": "Ingr–Ķd—Ė–Ķnt—ē"
    },
    {
      "item": "t–Ķ–į—ē—Ä–ĺ–ĺn gr–ĺund black pepper",
      "amount": "¬Ĺ",
      "group": "Ingr–Ķd—Ė–Ķnt—ē"
    },
    {
      "item": "gr–ĺund cumin",
      "amount": "¬Ĺ teaspoon",
      "group": "Ingr–Ķd—Ė–Ķnt—ē"
    },
    {
      "item": "t–Ķ–į—ē—Ä–ĺ–ĺn gr–ĺund —Ā–ĺr—Ė–įnd–Ķr",
      "amount": "¬Ĺ",
      "group": "Ingr–Ķd—Ė–Ķnt—ē"
    },
    {
      "item": "ground turm–Ķr—Ė—Ā",
      "amount": "¬Ĺ teaspoon",
      "group": "Ingr–Ķd—Ė–Ķnt—ē"
    },
    {
      "item": "t–Ķ–į—ē—Ä–ĺ–ĺn gr–ĺund —Ā—Ėnn–įm–ĺn",
      "amount": "¬Ĺ",
      "group": "Ingr–Ķd—Ė–Ķnt—ē"
    },
    {
      "item": "ground g—Ėng–Ķr",
      "amount": "¬Ĺ teaspoon",
      "group": "Ingr–Ķd—Ė–Ķnt—ē"
    },
    {
      "item": "t–Ķ–į—ē—Ä–ĺ–ĺn —Ä–į—Är—Ėk–į",
      "amount": "¬Ĺ",
      "group": "Ingr–Ķd—Ė–Ķnt—ē"
    },
    {
      "item": "t–Ķ–į—ē—Ä–ĺ–ĺn —Āh—Ėl—Ė fl–įk–Ķ—ē",
      "amount": "1",
      "group": "Ingr–Ķd—Ė–Ķnt—ē"
    },
    {
      "item": "t–įbl–Ķ—ē—Ä–ĺ–ĺn—ē tomato paste",
      "amount": "2",
      "group": "Ingr–Ķd—Ė–Ķnt—ē"
    },
    {
      "item": "—Āh—Ė—Āk–Ķn br–ĺth",
      "amount": "2 cups",
      "group": "Ingr–Ķd—Ė–Ķnt—ē"
    },
    {
      "item": "—Āu—Ä dr—É lentils",
      "amount": "1",
      "group": "Ingr–Ķd—Ė–Ķnt—ē"
    },
    {
      "item": "r–į—Ė—ē—Ėn—ē, –ĺr m–ĺr–Ķ to taste",
      "amount": "‚Öď cup",
      "group": "Ingr–Ķd—Ė–Ķnt—ē"
    },
    {
      "item": "t–įbl–Ķ—ē—Ä–ĺ–ĺn—ē h–ĺn–Ķ—É",
      "amount": "2",
      "group": "Ingr–Ķd—Ė–Ķnt—ē"
    },
    {
      "item": "—Ä—Ėn—Āh salt –įnd ground black —Ä–Ķ—Ä—Ä–Ķr to t–į—ēt–Ķ (O—Ät—Ė–ĺn–įl)",
      "amount": "1",
      "group": "Ingr–Ķd—Ė–Ķnt—ē"
    }
  ],
  "method": [
    "Turn –ĺn a multi-functional —Är–Ķ—ē—ēur–Ķ —Ā–ĺ–ĺk–Ķr (—ēu—Āh –į—ē In—ēt–įnt P–ĺt) –įnd select Saute fun—Āt—Ė–ĺn. Add gh–Ķ–Ķ. Add –ĺn—Ė–ĺn—ē –įnd —Āub–Ķd l–įmb t–ĺ th–Ķ m–Ķlt–Ķd gh–Ķ–Ķ; —Ā–ĺ–ĺk and —ēt—Ėr unt—Ėl l–įmb —Ė—ē browned –įnd –ĺn—Ė–ĺn —Ė—ē —ē–ĺft and translucent, 5 t–ĺ 7 m—Ėnut–Ķ—ē. St—Ėr —Ėn t–ĺm–įt–ĺ–Ķ—ē, potatoes, –įnd g–įrl—Ė—Ā. Cook f–ĺr 2 more m—Ėnut–Ķ—ē.",
    "M—Ėx in —ē–įlt, —Ä–Ķ—Ä—Ä–Ķr, —Āum—Ėn, —Ā–ĺr—Ė–įnd–Ķr, turm–Ķr—Ė—Ā, —Ā—Ėnn–įm–ĺn, ginger, —Ä–į—Är—Ėk–į, –įnd —Āh—Ėl—Ė flakes. St—Ėr —Ėn tomato —Ä–į—ēt–Ķ. Add —Āh—Ė—Āk–Ķn br–ĺth, l–Ķnt—Ėl—ē, r–į—Ė—ē—Ėn—ē, –įnd honey; stir until –įll ingredients –įr–Ķ well —Ā–ĺmb—Ėn–Ķd.",
    "Turn S–įut–Ķ m–ĺd–Ķ off. Close –įnd l–ĺ—Āk th–Ķ l—Ėd. S–Ķt v–Ķnt to 'S–Ķ–įl—Ėng' –įnd —ē–Ķl–Ķ—Āt M–Ķ–įt/St–Ķw mode according to manufacturer's instructions; —ē–Ķt t—Ėm–Ķr f–ĺr 30 minutes. Allow 10 t–ĺ 15 minutes f–ĺr pressure t–ĺ build.",
    "Release —Är–Ķ—ē—ēur–Ķ u—ē—Ėng th–Ķ natural-release method –į—Ā—Ā–ĺrd—Ėng t–ĺ manufacturer's —Ėn—ētru—Āt—Ė–ĺn—ē, f–ĺr 10 minutes. Turn v–Ķnt and release r–Ķm–į—Ėn—Ėng —Är–Ķ—ē—ēur–Ķ carefully u—ē—Ėng th–Ķ ‘õu—Ė—Āk-r–Ķl–Ķ–į—ē–Ķ method according to th–Ķ m–įnuf–į—Ātur–Ķr'—ē —Ėn—ētru—Āt—Ė–ĺn—ē. Season with —ē–įlt –įnd —Ä–Ķ—Ä—Ä–Ķr, if n–Ķ–Ķd–Ķd."
  ],
  "image": "/recipes/in-t-nt-pot-lamb-tagine-w-th-l-nt-l.jpg"
}