{
  "id": "parsley-coriander-and-dill-sauce",
  "name": "Parsley, Coriander and Dill Sauce",
  "source": {
    "cookbook": "Four Seasons",
    "author": "Mietta Sartori",
    "chapter": "Summer"
  },
  "servings": "serves 4–6",
  "ingredients": [
    {
      "item": "small bunch flat-leaf parsley",
      "amount": "1"
    },
    {
      "item": "bunch coriander",
      "amount": "½"
    },
    {
      "item": "bunch dill",
      "amount": "½"
    },
    {
      "item": "teaspoon Dijon mustard",
      "amount": "1"
    },
    {
      "item": "juice of 1 organic lemon",
      "amount": ""
    },
    {
      "item": "chilli (optional)",
      "amount": "1"
    },
    {
      "item": "organic egg yolk",
      "amount": "1"
    },
    {
      "item": "good-quality virgin olive oil",
      "amount": "250 ml"
    },
    {
      "item": "salt and ground black pepper",
      "amount": ""
    }
  ],
  "method": [
    "Place all the ingredients, except the oil and seasoning, in a food processor, and mix very well. Then add the oil very slowly, in a fine stream, as if you were making mayonnaise. The salsa verde should be quite thick in consistency. Add salt and pepper to taste.",
    "The herbs that go into a salsa verde (green sauce) can be a matter of taste. To accompany lamb, use flat-leaf parsley and mint. For grilled vegetables, you could use flat-leaf parsley and basil.",
    "If you want to keep it for a few days, pour it into a jar, bang the jar on the table to make sure there are no air pockets in the sauce and then pour a thin layer of virgin olive oil over it. Keep in the refrigerator for up to one week."
  ],
  "image": "/recipes/parsley-coriander-and-dill-sauce.jpg",
  "category": {
    "dish_type": [
      "side"
    ],
    "chapter": "Summer"
  },
  "time": {
    "prep": 10,
    "cook": 20,
    "total": 30
  },
  "cuisine": "Italian",
  "dietary": [
    "vegetarian",
    "gluten-free"
  ]
}
