{
  "id": "shanghai-eight-treasure-glutinous-rice",
  "name": "Shanghai Eight-Treasure Glutinous Rice",
  "source": {
    "cookbook": "Land of Fish and Rice",
    "author": "Fuchsia Dunlop",
    "chapter": "Sweet Dishes"
  },
  "ingredients": [
    {
      "item": "Japanese sweet rice",
      "amount": "1½ cups (250g)"
    },
    {
      "item": "superfine sugar, plus 3–4 tbsp",
      "amount": "1¼ cups (100g)"
    },
    {
      "item": "lard or coconut oil, or 4 tbsp groundnut oil, plus a little extra",
      "amount": "1½ oz (40g)"
    },
    {
      "item": "red bean paste",
      "amount": "5 oz (150g)"
    },
    {
      "item": "goji berries",
      "amount": "1 tbsp"
    },
    {
      "item": "glutinous rice flour, plus extra for dusting",
      "amount": "¾ cup (125g)"
    },
    {
      "item": "potato starch mixed with 6 tbsp cold water",
      "amount": "4 tbsp"
    },
    {
      "item": "large egg, beaten",
      "amount": "1"
    },
    {
      "item": "fermented glutinous rice wine",
      "amount": "½ cup (125ml)"
    },
    {
      "item": "candied osmanthus blossoms (optional)",
      "amount": "1 tbsp"
    },
    {
      "item": "whole heads dried silver-ear fungus, about 1½–2 oz (40–50g)",
      "amount": "2"
    },
    {
      "item": "goji berries",
      "amount": "3 tbsp"
    },
    {
      "item": "fermented glutinous rice wine",
      "amount": "4 tbsp"
    },
    {
      "item": "black sesame seeds",
      "amount": "2 oz (50g)"
    },
    {
      "item": "all-purpose flour",
      "amount": "3 tbsp"
    },
    {
      "item": "superfine sugar",
      "amount": "2 oz (50g)"
    },
    {
      "item": "lard or coconut oil",
      "amount": "3 oz (75g)"
    },
    {
      "item": "glutinous rice flour, plus extra for dusting",
      "amount": "1½ cups (250g)"
    },
    {
      "item": "cooking oil",
      "amount": "1 tsp"
    },
    {
      "item": "red bean paste",
      "amount": "5 oz (150g)"
    },
    {
      "item": "glutinous rice flour, plus extra for dusting",
      "amount": "1¾ cups (275g)"
    },
    {
      "item": "slice of pumpkin",
      "amount": "1 lb (500g)"
    },
    {
      "item": "cooking oil",
      "amount": "1¾ cups (400ml)"
    },
    {
      "item": "New Year’s rice cake, in strips or round slices",
      "amount": "10 oz (300g)"
    },
    {
      "item": "powdered sugar",
      "amount": "3 tbsp"
    },
    {
      "item": "osmanthus blossom jam or 1 tbsp dried osmanthus blossoms",
      "amount": "1½ tbsp"
    },
    {
      "item": "aonori-ko seaweed flakes",
      "amount": "1½ tbsp"
    }
  ],
  "method": [
    "Cover the goji berries with cold water and leave them for half an hour to soften. Put the glutinous rice flour in a bowl and gradually mix in enough tepid water to make a putty-like dough; it should not stick to your fingers. Break off little pieces of dough and roll them into balls the size of shelled hazelnuts. Set aside on a board dusted with a little rice flour.",
    "Cover the silver-ear fungus generously with cold water and leave to soak for an hour or so, until supple. Use a knife or scissors to snip out the tight, hard centers of each head, along with any discolored parts. Use your fingers to break the heads apart into small clumps. Rinse well to remove any grit, then drain.",
    "Put the cleaned silver-ear in a pan, cover with about 2 quarts (2 liters) cold water, bring to the boil and simmer over a very low flame for about 1½ hours, until soft and heavy. Add the rock sugar and stir to dissolve. Simmer for another 30 minutes or so, stirring frequently so the silver-ear doesn’t stick to the pan. Set aside, and for best results leave overnight to settle, by which time the silver-ear will be soft and voluptuous, the liquid sleepy and heavy.",
    "Put the glutinous rice flour in a bowl and gradually mix in the cooking oil and enough tepid water to make a putty-like dough; it should not stick to your fingers. Break the dough into pieces and roll into balls a little larger than the stuffing balls, dusting the work surface with rice flour as necessary. Press your thumb into the center of each ball to make a cup. Press a frozen stuffing ball into each cup and draw up the dough around it to enclose it completely.",
    "Bring a pan of water to the boil, add the rice balls and simmer until they float. Serve about 4 balls per person in a bowl of the hot cooking water. Sprinkle over a few osmanthus blossoms, if you have them.",
    "Cooking oil for deep- frying, plus 2 tsp",
    "Heat the oil for deep-frying to 300°F (150°C). Fry the pumpkin cakes in batches over a medium flame for about 8 minutes, until golden. The oil should fizz around the cakes, but not too aggressively—you want them to cook slowly enough to melt the lard in the stuffing, and to avoid bursting them open. Serve hot.",
    "Heat the oil in a seasoned wok over a high flame to 300°F (150°C). Carefully slide the pieces of rice cake into the oil and deep-fry for 2–3 minutes, until they are slightly puffy. While they fry, use a wok scoop to separate them. Remove the rice cake pieces from the oil with a slotted spoon and set aside. Carefully pour off the oil into a heatproof container."
  ],
  "time": {
    "total": 38
  },
  "category": {
    "dish_type": [
      "side"
    ],
    "chapter": "Sweet Dishes"
  },
  "image": "/recipes/shanghai-eight-treasure-glutinous-rice.jpg",
  "cuisine": "Chinese"
}
